tornadoapi/__init__.py
tornadoapi/fields.py
tornadoapi/handler.py
tornadoapi/validators.py
tornadoapi/conf/__init__.py
tornadoapi/conf/global_settings.py
tornadoapi/core/__init__.py
tornadoapi/core/code.py
tornadoapi/core/err_code.py
tornadoapi/core/exceptions.py
tornadoapi/core/functional.py
tornadoapi/core/log.py
tornadoapi/core/module_loading.py
tornadoapi/core/traceback.py
tornadoapi/core/mail/__init__.py
tornadoapi/core/mail/message.py
tornadoapi/core/mail/utils.py
tornadoapi/core/mail/backends/__init__.py
tornadoapi/core/mail/backends/base.py
tornadoapi/core/mail/backends/smtp.py
tornadoapi/resource/apiview.html
tornadoapi/resource/doc.html
tornadoapi/resource/technical_500.html
tornadoapi/resource/technical_500.txt
tornadoapi/storage/__init__.py
tornadoapi/storage/cache.py
tornadoapi/storage/kvstorage.py
tornadoapi/storage/memorystorage.py
tornadoapi/template/__init__.py
tornadoapi/template/jinja2_loader.py
tornadoapi-1.1.6.dist-info/DESCRIPTION.rst
tornadoapi-1.1.6.dist-info/METADATA
tornadoapi-1.1.6.dist-info/RECORD
tornadoapi-1.1.6.dist-info/WHEEL
tornadoapi-1.1.6.dist-info/metadata.json
tornadoapi-1.1.6.dist-info/top_level.txt
