Metadata-Version: 2.0
Name: tornadoapi
Version: 1.1.6
Summary: Tornado REST framework
Home-page: https://github.com/007gzs/tornado-rest-framework
Author: 007gzs
Author-email: 007gzs@gmail.com
License: LGPL v3
Keywords: tornado rest framework api view
Platform: UNKNOWN
Classifier: Development Status :: 3 - Alpha
Classifier: Intended Audience :: Developers
Classifier: Topic :: Software Development :: Build Tools
Classifier: License :: OSI Approved :: GNU Lesser General Public License v3 (LGPLv3)
Classifier: Programming Language :: Python :: 2
Classifier: Programming Language :: Python :: 2.7
Classifier: Programming Language :: Python :: 3
Classifier: Programming Language :: Python :: 3.3
Classifier: Programming Language :: Python :: 3.4
Classifier: Programming Language :: Python :: 3.5
Classifier: Programming Language :: Python :: 3.6
Requires-Dist: six (>=1.8.0)
Requires-Dist: jinja2
Requires-Dist: tornado
Provides-Extra: dev
Requires-Dist: check-manifest; extra == 'dev'
Provides-Extra: test
Requires-Dist: coverage; extra == 'test'
